Metadata-Version: 2.1
Name: msqlparse
Version: 0.4.4
Summary: A non-validating SQL parser.
Home-page: https://github.com/andialbrecht/sqlparse
Author: Andi Albrecht
Author-email: albrecht.andi@gmail.com
License: BSD-3-Clause
Project-URL: Documentation, https://sqlparse.readthedocs.io/
Project-URL: Release Notes, https://sqlparse.readthedocs.io/en/latest/changes/
Project-URL: Source, https://github.com/andialbrecht/sqlparse
Project-URL: Tracker, https://github.com/andialbrecht/sqlparse/issues
Classifier: Development Status :: 5 - Production/Stable
Classifier: Intended Audience :: Developers
Classifier: License :: OSI Approved :: BSD License
Classifier: Operating System :: OS Independent
Classifier: Programming Language :: Python
Classifier: Programming Language :: Python :: 3
Classifier: Programming Language :: Python :: 3 :: Only
Classifier: Programming Language :: Python :: 3.8
Classifier: Programming Language :: Python :: 3.9
Classifier: Programming Language :: Python :: 3.10
Classifier: Programming Language :: Python :: Implementation :: CPython
Classifier: Programming Language :: Python :: Implementation :: PyPy
Classifier: Topic :: Database
Classifier: Topic :: Software Development
Requires-Python: >=3.8
License-File: LICENSE
License-File: AUTHORS
